hundred_hammers/__init__.py
hundred_hammers/base.py
hundred_hammers/classifier.py
hundred_hammers/config.py
hundred_hammers/hyperparam_info.py
hundred_hammers/hyperparameters.py
hundred_hammers/metric_alias.py
hundred_hammers/model_zoo.py
hundred_hammers/plots.py
hundred_hammers/regressor.py
hundred_hammers/utils.py
hundred_hammers-1.0.5.dist-info/LICENSE
hundred_hammers-1.0.5.dist-info/METADATA
hundred_hammers-1.0.5.dist-info/WHEEL
hundred_hammers-1.0.5.dist-info/top_level.txt
hundred_hammers-1.0.5.dist-info/RECORD
