Metadata-Version: 2.1
Name: hundred-hammers
Version: 1.0.5
Summary: Quickly try out several ML models on a given dataset
Home-page: http://github.com/vgarciasc/hundred_hammers
Author: Vinicius Garcia
Author-email: Vinícius Garcia <vinizinho@vinizinho.net>
License: MIT
Project-URL: Homepage, https://github.com/vgarciasc/hundred-hammers
Project-URL: Bug Tracker, https://github.com/vgarciasc/hundred-hammers/issues
Classifier: Programming Language :: Python :: 3
Classifier: License :: OSI Approved :: MIT License
Classifier: Operating System :: OS Independent
Requires-Python: >=3.10
License-File: LICENSE
Requires-Dist: seaborn
Requires-Dist: matplotlib
Requires-Dist: adjustText
Requires-Dist: scikit-learn
Requires-Dist: scikit-elm
Requires-Dist: xgboost >=1.7.6
Requires-Dist: pandas
Requires-Dist: tqdm
Requires-Dist: dask
Requires-Dist: dask[distributed]
Requires-Dist: schema
Requires-Dist: pytest
